cricinfo/__init__.py
cricinfo/cricbuzz.py
pycricbuzz/__init__.py
pycricbuzz/cricbuzz.py
cricinfo-1.2.5.dist-info/LICENSE.txt
cricinfo-1.2.5.dist-info/METADATA
cricinfo-1.2.5.dist-info/WHEEL
cricinfo-1.2.5.dist-info/top_level.txt
cricinfo-1.2.5.dist-info/RECORD
