Metadata-Version: 2.1
Name: cricinfo
Version: 1.2.5
Summary: A library for fetching live cricket scores from cricbuzz
Home-page: https://github.com/pranith7/cricinfo
Author: Pranith Pashikanti
Author-email: pashikantipranith7867@gmail.com
License: GPLv2
Keywords: cricket,cricbuzz
License-File: LICENSE.txt
Requires-Dist: requests
Requires-Dist: beautifulsoup4
